{"cameraMode":{"drawMode":0,"name":"Shaded","section":"Shading Mode"},"sceneLighting":true,"audioPlay":false,"sceneViewState":{"m_AlwaysRefresh":false,"showFog":true,"showSkybox":true,"showFlares":true,"showImageEffects":true,"showParticleSystems":true,"showVisualEffectGraphs":true,"m_FxEnabled":true},"in2DMode":false,"pivot":{"x":0.06935006380081177,"y":2.254599094390869,"z":-7.818792819976807},"rotation":{"x":-0.0019447318045422435,"y":-0.9974108934402466,"z":-0.067424476146698,"w":0.027272017672657968},"size":6.771562099456787,"orthographic":false}